boomber/__init__.py
boomber/cli.py
boomber/main.py
boomber/service.py
boomber/utils.py
boomber/app/__init__.py
boomber/app/main.py
boomber/app/models.py
boomber/app/status.py
boomber/app/routers/__init__.py
boomber/app/routers/attack.py
boomber/app/routers/index.py
boomber/app/routers/services.py
boomber/app/static/css/bootstrap.min.css
boomber/app/static/css/bootstrap.min.css.map
boomber/app/static/css/index.css
boomber/app/static/css/intlTelInput.min.css
boomber/app/static/img/flags.png
boomber/app/static/img/flags@2x.png
boomber/app/static/js/index.js
boomber/app/static/js/intlTelInput.min.js
boomber/app/static/js/progressbar.min.js
boomber/app/static/js/progressbar.min.js.map
boomber/app/templates/index.html
boomber/services/3040.py
boomber/services/585gold.py
boomber/services/585zolotoy.py
boomber/services/aisttaxi.py
boomber/services/alfalife.py
boomber/services/alpari.py
boomber/services/apteka.py
boomber/services/atprime.py
boomber/services/av.py
boomber/services/avtoobzvon.py
boomber/services/bamperby.py
boomber/services/bartokyo.py
boomber/services/beltelecom.py
boomber/services/benzuber.py
boomber/services/bluefin.py
boomber/services/boosty.py
boomber/services/buzzols.py
boomber/services/call2friends.py
boomber/services/callmyphone.py
boomber/services/carsmile.py
boomber/services/chefmarket.py
boomber/services/cian.py
boomber/services/cinema5.py
boomber/services/citilink.py
boomber/services/city24.py
boomber/services/cleversite.py
boomber/services/creditter.py
boomber/services/crossstudio.py
boomber/services/delimobil.py
boomber/services/dianet.py
boomber/services/dns_shop.py
boomber/services/easypay.py
boomber/services/edostav.py
boomber/services/egroshi.py
boomber/services/eldorado.py
boomber/services/esh_derevenskoe.py
boomber/services/etm.py
boomber/services/fiestapizza.py
boomber/services/finam.py
boomber/services/findclone.py
boomber/services/fixprice.py
boomber/services/flashcall.py
boomber/services/flipkart.py
boomber/services/foodband.py
boomber-3.1.4.3.dist-info/LICENSE
boomber-3.1.4.3.dist-info/METADATA
boomber-3.1.4.3.dist-info/WHEEL
boomber-3.1.4.3.dist-info/entry_points.txt
boomber-3.1.4.3.dist-info/top_level.txt
boomber-3.1.4.3.dist-info/RECORD
